Modion/D3PLOT/__init__.py
Modion/D3PLOT/placeholder.py
modion_d3plot-0.0.1.dist-info/LICENSE
modion_d3plot-0.0.1.dist-info/METADATA
modion_d3plot-0.0.1.dist-info/WHEEL
modion_d3plot-0.0.1.dist-info/top_level.txt
modion_d3plot-0.0.1.dist-info/RECORD
